{
    "Channel_Name": "tseries",
    "Join_Date": "2006-03-13T14:27:05Z",
    "Parsed_email_ids": [],
    "Status": "Processed",
    "Subscriber_Count": "245000000",
    "Timestamp": "1688905912",
    "Views": "227822846936",
    "latest_videos": [
        {
            "Comment_word_cloud": {},
            "Comments Count": "0",
            "Title": "Chinese | Shetty Saa | MTV Hustle | Let The Hustle Begin!",
            "sentiment_score": 0
        },
        {
            "Comment_word_cloud": {
                "99th": 1,
                "First": 1,
                "Glitch": 1,
                "Sbhi": 1,
                "Sirf": 1,
                "comment": 1,
                "hai": 2,
                "jarhi": 1,
                "karta": 1,
                "kaun": 1,
                "ko": 1,
                "kya": 1,
                "kyaa": 1,
                "nothing": 1,
                "series": 3,
                "viewer": 1,
                "views": 3
            },
            "Comments Count": "0",
            "Title": "Road Pe | Shetty Saa | MTV Hustle | Let The Hustle Begin!",
            "sentiment_score": 0.032836363636363636
        },
        {
            "Comment_word_cloud": {
                "399m": 1,
                "Bhaiii": 1,
                "Early": 1,
                "HALLO": 1,
                "Hello": 1,
                "Hiiiiiiiiiii": 1,
                "INDONESIA": 1,
                "Jai": 1,
                "Le": 1,
                "MC": 1,
                "Mast": 1,
                "Ram": 2,
                "Shri": 1,
                "Square": 1,
                "Super": 1,
                "bar": 1,
                "bro": 1,
                "button": 2,
                "coment": 1,
                "everyone": 1,
                "fan": 1,
                "fast": 1,
                "hai": 1,
                "heard": 2,
                "href": 1,
                "invalid zCSafez": 1,
                "jai": 2,
                "lets": 1,
                "mahakal": 1,
                "mee": 1,
                "pahli": 1,
                "rAm": 1,
                "rap": 2,
                "sereis": 1,
                "series": 2,
                "shri": 1,
                "song": 1,
                "subscribers": 1,
                "uttarakhand": 1,
                "wtf": 1,
                "Перший": 1,
                "क": 1,
                "करत": 1,
                "ग": 1,
                "द": 1,
                "न": 1,
                "पस": 1,
                "ल": 1,
                "स": 1,
                "ह": 1
            },
            "Comments Count": "0",
            "Title": "Stage Pe | Shetty Saa | MTV Hustle | Let The Hustle Begin!",
            "sentiment_score": 0.11166499999999999
        },
        {
            "Comment_word_cloud": {
                "Bhai": 1,
                "Cringhe": 1,
                "Fast": 1,
                "Har": 1,
                "Heard": 1,
                "Jai": 1,
                "Jo": 1,
                "Kis": 1,
                "Kon": 1,
                "Live": 1,
                "MrBeast": 1,
                "Papa": 1,
                "RcR": 1,
                "Rcr": 1,
                "Sub": 1,
                "andar": 1,
                "apload": 1,
                "baar": 1,
                "better": 1,
                "bigg": 1,
                "boss": 2,
                "bots": 1,
                "chahiye": 1,
                "channel": 1,
                "chayta": 1,
                "comment": 1,
                "dead": 1,
                "ek": 1,
                "fukra": 1,
                "ghati": 1,
                "hai": 1,
                "hindutvavadi": 1,
                "hurayy": 1,
                "insaan": 1,
                "jai": 1,
                "janma": 1,
                "jeta": 1,
                "ka": 3,
                "kar": 1,
                "karne": 1,
                "ke": 1,
                "ki": 1,
                "kte": 1,
                "level": 1,
                "liya": 1,
                "mahadev": 1,
                "mahakaal": 1,
                "mahakal": 1,
                "mrbeast": 1,
                "ne": 1,
                "next": 1,
                "payar": 1,
                "pe": 1,
                "promotion": 1,
                "ram": 1,
                "rap": 2,
                "sabhi": 1,
                "sabhyata": 1,
                "sawan": 1,
                "se": 1,
                "season": 2,
                "shree": 1,
                "sindhu": 1,
                "song": 1,
                "tha": 1,
                "thi": 1,
                "vale": 1,
                "video": 1,
                "week": 1,
                "Намана": 1,
                "русский": 1,
                "я": 1,
                "اول": 1,
                "عراقي": 1
            },
            "Comments Count": "30",
            "Title": "Aaja Mere Nede | RCR | MTV Hustle | Let The Hustle Begin!",
            "sentiment_score": 0.024499999999999994
        },
        {
            "Comment_word_cloud": {
                "1st": 1,
                "245M": 1,
                "42army": 1,
                "Bhagat": 1,
                "Jise": 1,
                "Mr": 1,
                "MrBeast": 1,
                "Nice": 2,
                "Oppo": 1,
                "Rcr": 1,
                "Shaheedi": 1,
                "Singh": 1,
                "Super": 2,
                "Valentime": 1,
                "accha": 1,
                "attack": 1,
                "barabar": 1,
                "beast": 1,
                "better": 1,
                "big": 1,
                "boss": 1,
                "day": 1,
                "fan": 1,
                "gana": 1,
                "h": 1,
                "ki": 1,
                "lagta": 1,
                "nice": 1,
                "rate": 1,
                "rcr": 1,
                "song": 1,
                "subs": 1,
                "video": 1,
                "viewer": 2,
                "views": 1,
                "vo": 1,
                "ye": 1
            },
            "Comments Count": "25",
            "Title": "Facts | RCR | MTV Hustle | Let The Hustle Begin!",
            "sentiment_score": 0.2175736842105263
        },
        {
            "Comment_word_cloud": {
                "Bari": 1,
                "First": 1,
                "HV": 1,
                "Hii": 1,
                "Kalam": 1,
                "Kon": 1,
                "Love": 1,
                "MrBeast": 1,
                "Nice": 1,
                "Osm": 2,
                "Rcr": 1,
                "Superb": 1,
                "aj": 1,
                "ate": 1,
                "aur": 1,
                "baki": 1,
                "bella": 1,
                "big": 1,
                "boss": 1,
                "br": 1,
                "bro": 1,
                "fan": 1,
                "father": 1,
                "first": 1,
                "freind": 1,
                "hai": 3,
                "heart": 1,
                "hota": 1,
                "inka": 1,
                "kash": 1,
                "ki": 1,
                "kro": 1,
                "masterpiece": 1,
                "mujhe": 1,
                "nasib": 1,
                "nice": 1,
                "peyaar": 1,
                "place": 1,
                "please": 1,
                "rab": 1,
                "rap": 1,
                "song": 1,
                "sub": 1,
                "surprise": 1,
                "take": 1,
                "u": 1,
                "v": 1,
                "wo": 1,
                "ye": 1,
                "Я": 1,
                "русский": 1,
                "अम": 1,
                "इ": 1,
                "इस": 1,
                "क": 1,
                "करत": 1,
                "ख": 1,
                "त": 1,
                "द": 1,
                "न": 1,
                "नह": 1,
                "प": 1,
                "म": 1,
                "मन": 1,
                "य": 1,
                "र": 1,
                "स": 1,
                "ह": 1
            },
            "Comments Count": "21",
            "Title": "Father | RCR | MTV Hustle | Let The Hustle Begin!",
            "sentiment_score": 0.16773499999999997
        },
        {
            "Comment_word_cloud": {
                "000р": 1,
                "2020г": 1,
                "21k": 1,
                "23г": 1,
                "240m": 1,
                "24k": 1,
                "38k": 1,
                "Ariyan": 1,
                "Awesome": 1,
                "BLOCKBUSTER": 1,
                "Bht": 1,
                "Biza": 1,
                "Bollywood": 1,
                "Channel": 1,
                "Colorful": 1,
                "Comment": 1,
                "Dan": 1,
                "First": 1,
                "Great": 1,
                "Heart": 1,
                "Homiestock": 1,
                "Ishq": 2,
                "Kara": 1,
                "Kartik": 2,
                "Kiara": 1,
                "Kon": 1,
                "LOADING": 1,
                "Love": 3,
                "MRBEAST": 1,
                "Malhotra": 1,
                "Mistaken": 1,
                "Music": 1,
                "Nice": 4,
                "Please": 1,
                "Pokoknya": 1,
                "Pyar": 1,
                "Rules": 1,
                "Song": 1,
                "Stop": 1,
                "Subhrajit": 1,
                "TOOOP": 1,
                "Whoes": 1,
                "aaye": 1,
                "advani": 1,
                "aik": 1,
                "aisa": 1,
                "always": 3,
                "baaki": 1,
                "baar": 1,
                "baja": 1,
                "boring": 1,
                "bot": 2,
                "br": 5,
                "channel": 3,
                "comments": 1,
                "content": 2,
                "dam": 1,
                "day": 3,
                "de": 1,
                "dekh": 1,
                "ek": 1,
                "energetic": 1,
                "every": 1,
                "fck": 1,
                "feel": 1,
                "first": 1,
                "fun": 1,
                "gaana": 1,
                "h": 1,
                "hacemucho": 1,
                "hai": 4,
                "hain": 1,
                "ham": 1,
                "hasta": 1,
                "heart": 1,
                "hi": 1,
                "ho": 1,
                "hours": 1,
                "hrs": 1,
                "jodi": 1,
                "kam": 1,
                "karo": 1,
                "karty": 1,
                "keren": 1,
                "kis": 1,
                "lia": 1,
                "lights": 1,
                "liya": 1,
                "lo": 1,
                "long": 1,
                "los": 1,
                "lot": 1,
                "love": 1,
                "lyrical": 1,
                "main": 1,
                "mantab": 1,
                "mejor": 1,
                "miauuu": 1,
                "mood": 1,
                "movie": 1,
                "much": 1,
                "mujhe": 1,
                "music": 1,
                "nahi": 1,
                "ne": 2,
                "never": 1,
                "next": 1,
                "padne": 1,
                "passionate": 1,
                "people": 1,
                "pierde": 1,
                "please": 1,
                "plzz": 1,
                "post": 1,
                "prajeet": 1,
                "raat": 1,
                "rabba": 1,
                "raha": 1,
                "release": 1,
                "rulaya": 1,
                "sad": 1,
                "second": 1,
                "series": 4,
                "siddhart": 1,
                "soft": 1,
                "song": 7,
                "songs": 1,
                "story": 2,
                "sub": 2,
                "subs": 1,
                "subscribed": 1,
                "subscribers": 1,
                "sunyai": 1,
                "tf": 1,
                "thank": 1,
                "today": 1,
                "vairal": 1,
                "video": 5,
                "views": 4,
                "whole": 1,
                "wo": 1,
                "ya": 1,
                "ye": 1,
                "years": 1,
                "youtuber": 1,
                "АДЛЕРЕ": 1,
                "Антоновна": 1,
                "Антоновной": 1,
                "Виталий": 1,
                "Воробец": 1,
                "Вячеславовна": 1,
                "ГПК": 1,
                "ДА": 1,
                "ДВУХ": 1,
                "Девиз": 1,
                "ИЛИ": 1,
                "Им": 1,
                "Ирина": 1,
                "Ириной": 1,
                "Китаю": 1,
                "Китая": 1,
                "Князева": 1,
                "Круто": 1,
                "Крым": 1,
                "МЫ": 1,
                "Назаренко": 1,
                "Новокузнецка": 1,
                "Новокузнецке": 1,
                "Нұр": 1,
                "Нұрсұлтан": 1,
                "ОБЩЕСТВЕННЫЙ": 1,
                "Оксана Сергеевна": 1,
                "ПРИСТАВОВ": 1,
                "Плотникова": 1,
                "Подписчики": 1,
                "Просмотры": 1,
                "Путин": 1,
                "РЕЗОНАНС": 1,
                "РФ": 1,
                "России": 1,
                "Россия": 1,
                "Румынии": 1,
                "Румынию": 1,
                "Сочи": 1,
                "Тайвань": 1,
                "Украину": 1,
                "Уриевский": 1,
                "ХОТЯТ": 1,
                "ЦРУ": 1,
                "ЧЕЛОВЕК": 1,
                "Что": 1,
                "Юрьевич": 1,
                "а": 1,
                "алам": 1,
                "алчных": 1,
                "алы": 2,
                "английском": 1,
                "армии": 1,
                "асфальте": 1,
                "б": 1,
                "барлық": 1,
                "боевое": 1,
                "божий": 1,
                "болар": 1,
                "более": 1,
                "бір": 1,
                "в": 1,
                "вас": 1,
                "везде": 1,
                "весь": 1,
                "взятки": 1,
                "виндоуз": 1,
                "во": 1,
                "все": 1,
                "всем": 1,
                "гипнозом": 1,
                "гипнозу": 1,
                "глазах": 1,
                "грабанут": 1,
                "грабительницей": 1,
                "грабительницу": 1,
                "да": 1,
                "де": 1,
                "деловой": 1,
                "деп": 1,
                "для": 1,
                "дочери": 1,
                "еді": 1,
                "емес": 1,
                "ему": 1,
                "если": 1,
                "есімі": 1,
                "жителей": 1,
                "жительства": 1,
                "жолдарын": 1,
                "және": 1,
                "за": 2,
                "забрать": 1,
                "заговорила": 1,
                "и": 1,
                "иероглифами": 1,
                "иероглифы": 1,
                "из": 1,
                "изымать": 1,
                "имущество": 1,
                "иск": 1,
                "истец": 1,
                "к": 2,
                "как": 1,
                "келісім": 1,
                "кинет": 1,
                "клеветой": 1,
                "княгиня": 1,
                "коммент": 1,
                "коттеджи": 1,
                "ладно": 1,
                "лёгкую": 1,
                "машины": 1,
                "мен": 2,
                "меня": 1,
                "месту": 1,
                "миллиарды": 1,
                "мне": 1,
                "мозг": 1,
                "мой": 1,
                "мясо": 1,
                "мәселелерді": 1,
                "на": 1,
                "надо": 1,
                "называл": 1,
                "напичкаем": 1,
                "нарушение": 1,
                "нас": 1,
                "начали": 1,
                "не": 1,
                "ней": 1,
                "нет": 1,
                "ни": 1,
                "ниже": 1,
                "но": 1,
                "нып": 1,
                "о": 1,
                "обе": 1,
                "ограбят": 1,
                "он": 1,
                "она": 1,
                "она же": 1,
                "оның": 1,
                "оружием": 1,
                "оскорбление": 1,
                "осталось": 1,
                "от": 1,
                "ответчик": 1,
                "ответчика": 1,
                "отключат": 1,
                "патриотично": 1,
                "по": 1,
                "под": 1,
                "подеётся": 1,
                "подогнуть": 1,
                "потеряет": 1,
                "потеряла": 1,
                "потом": 1,
                "почему": 1,
                "пригрозило": 1,
                "прихвостням": 1,
                "продажным": 1,
                "прокуратуру": 1,
                "прописан": 1,
                "против": 1,
                "пулемётам": 1,
                "пулемётообразным": 1,
                "рассценили": 1,
                "ретінде": 1,
                "родины": 1,
                "румынская": 1,
                "с": 1,
                "своей": 1,
                "себе": 1,
                "сейчас": 1,
                "сети": 1,
                "скоро": 1,
                "славянина": 1,
                "смогла": 1,
                "сможет": 1,
                "смотри": 1,
                "снято": 1,
                "со": 1,
                "справедливо": 1,
                "ст": 1,
                "стольким": 1,
                "стороны": 1,
                "страна": 1,
                "стреляет": 1,
                "суд": 1,
                "суде": 1,
                "суды": 1,
                "судью": 1,
                "судья": 1,
                "судьёй": 1,
                "так": 1,
                "тебя": 1,
                "то": 1,
                "тот": 1,
                "тронет": 1,
                "түрі": 1,
                "у": 1,
                "уже": 1,
                "цыгане": 1,
                "цыганей": 1,
                "цыганка": 1,
                "цыганки": 1,
                "цыганку": 1,
                "цыганская": 1,
                "цыганским": 1,
                "цыганской": 1,
                "чавелы": 1,
                "чести": 1,
                "чиновникам": 1,
                "чиновников": 1,
                "что": 1,
                "шешу": 1,
                "шыгад": 1,
                "эмалью": 1,
                "это": 1,
                "юрисдикцию": 1,
                "я": 1,
                "Қоғамдық": 1,
                "қолданылады": 1,
                "үстіне": 1,
                "इस": 1,
                "क": 1,
                "ग": 1,
                "ज": 1,
                "न": 1,
                "नत": 1,
                "भ": 1,
                "र": 1,
                "स": 1,
                "ह": 1
            },
            "Comments Count": "115",
            "Title": "Aaj Ke Baad-Reprise (Lyrical)SatyaPrem Ki Katha| Kartik,Kiara|Manan Bhardwaj, Himani |Sajid N,Sameer",
            "sentiment_score": 0.11298701298701298
        },
        {
            "Comment_word_cloud": {
                "0m42s": 1,
                "1st": 2,
                "2m34s": 1,
                "BHAIYA": 1,
                "BOSSSSSSSSS": 1,
                "Best": 1,
                "Chutiye": 1,
                "Comments": 1,
                "Epic": 1,
                "First": 1,
                "Fist": 1,
                "Form": 1,
                "Garv": 1,
                "Great": 1,
                "HAT": 1,
                "Hain": 1,
                "HairStyle": 1,
                "Hindu": 1,
                "Insta": 1,
                "JAY": 1,
                "JIcsSYkJ5gQ": 2,
                "Jai": 2,
                "Jatt": 1,
                "KE": 1,
                "Kon": 1,
                "Love": 1,
                "Mahadev": 2,
                "Mast": 1,
                "New": 1,
                "Nice": 7,
                "Op": 1,
                "Peru": 1,
                "RAM": 1,
                "SHRI": 1,
                "Singhnd": 1,
                "Sukh": 1,
                "Sukhi": 1,
                "WILLCONO": 1,
                "Weeknd": 1,
                "Yo": 1,
                "aaya": 1,
                "ab": 1,
                "artist": 1,
                "aur": 1,
                "aya": 1,
                "big": 1,
                "brothers": 1,
                "chalo": 1,
                "click": 1,
                "comment": 2,
                "comments": 1,
                "dance": 1,
                "dekhen": 1,
                "e": 1,
                "fan": 1,
                "first": 1,
                "flim": 1,
                "gany": 1,
                "good": 1,
                "gt": 1,
                "h": 2,
                "hai": 2,
                "ham": 1,
                "highlights": 1,
                "href": 2,
                "https": 2,
                "jadu": 1,
                "jogi": 1,
                "kaho": 1,
                "kare": 1,
                "laty": 1,
                "mahadve": 1,
                "much": 1,
                "music": 3,
                "new": 1,
                "ni": 1,
                "nice": 1,
                "par": 1,
                "perfect": 1,
                "rajstan": 1,
                "ram": 2,
                "reeler": 1,
                "reels": 1,
                "sab": 1,
                "series": 1,
                "shree": 2,
                "siries": 1,
                "song": 6,
                "st": 1,
                "story": 1,
                "top": 1,
                "v": 2,
                "watch": 2,
                "youtube": 2
            },
            "Comments Count": "57",
            "Title": "Jogi (Lyrical) Sukh-E Muzical Doctorz | MNLTX | Nagii | Amanninder Singh | Punjabi Songs 2023",
            "sentiment_score": 0.14078431372549022
        },
        {
            "Comment_word_cloud": {
                "3য": 1,
                "4k": 1,
                "Aaryan": 1,
                "Aaunga": 1,
                "Apni": 1,
                "Arijit": 1,
                "BLOCKBUSTER": 1,
                "Baki": 1,
                "Best": 1,
                "Bro": 1,
                "Cham": 2,
                "Channel": 1,
                "Different": 1,
                "Everyone": 1,
                "Experience": 1,
                "Good": 1,
                "Great": 1,
                "Hindu": 1,
                "Imagine": 1,
                "Iska": 1,
                "JAI": 1,
                "Jisko": 1,
                "Kare": 1,
                "Karo": 2,
                "Karthik": 1,
                "Kartik": 5,
                "Kartik과": 1,
                "Ke": 1,
                "Ki": 1,
                "Kiara": 3,
                "Kis": 1,
                "LOADING": 1,
                "Lambi": 1,
                "Le": 1,
                "Liye": 1,
                "Looks": 1,
                "Love": 1,
                "Maa": 1,
                "Melody": 1,
                "Monali": 3,
                "Mr": 1,
                "Music": 2,
                "Nice": 5,
                "Perfect": 2,
                "Please": 4,
                "RAM": 1,
                "Raat": 1,
                "Release": 2,
                "SHREE": 1,
                "Song": 1,
                "SuPeR": 1,
                "TV": 1,
                "Thakur": 2,
                "Theatre": 2,
                "Umar": 1,
                "Video": 2,
                "Wow": 2,
                "Ye": 1,
                "YouTube": 1,
                "aaya": 1,
                "accha": 1,
                "actor": 1,
                "actress": 2,
                "aku": 1,
                "always": 1,
                "amp": 1,
                "asap": 1,
                "assemble": 1,
                "baghi": 1,
                "bahut": 1,
                "beast": 1,
                "beautiful": 2,
                "best": 3,
                "bhai": 2,
                "bhaiya": 1,
                "bhi": 1,
                "bhole": 1,
                "blowing": 1,
                "bots": 2,
                "br": 6,
                "bro": 1,
                "bros": 1,
                "cahiye": 1,
                "calmness": 1,
                "channel": 1,
                "couple": 2,
                "cute": 2,
                "dalte": 1,
                "dance": 1,
                "dreams": 1,
                "duniya": 1,
                "even": 1,
                "everything": 1,
                "fans": 1,
                "fantastic": 2,
                "favourite": 1,
                "feel": 1,
                "feet": 1,
                "forward": 1,
                "full": 2,
                "gonna": 1,
                "good": 3,
                "guys": 2,
                "hai": 3,
                "heart": 2,
                "heaven": 1,
                "hi": 2,
                "ii": 1,
                "jai": 1,
                "joke": 1,
                "ka": 3,
                "kar": 1,
                "kare": 1,
                "karo": 1,
                "kattah": 1,
                "kgf": 1,
                "ki": 2,
                "kiara": 1,
                "ko": 1,
                "kyu": 1,
                "laga": 1,
                "life": 1,
                "log": 1,
                "long": 1,
                "love": 3,
                "magic": 1,
                "man": 1,
                "many": 1,
                "mast": 1,
                "matter": 1,
                "melody": 1,
                "mind": 1,
                "movie": 4,
                "much": 1,
                "mulu": 1,
                "music": 3,
                "never": 2,
                "nhi": 1,
                "nice": 1,
                "nikalo": 1,
                "old": 1,
                "parents": 1,
                "pasand": 1,
                "peeth": 1,
                "perfect": 2,
                "performance": 1,
                "please": 1,
                "plss": 1,
                "post": 1,
                "products": 1,
                "reason": 1,
                "reet": 1,
                "release": 4,
                "sab": 1,
                "salaar": 1,
                "samne": 1,
                "se": 1,
                "sequence": 1,
                "series": 1,
                "short": 1,
                "sir": 1,
                "song": 28,
                "songs": 1,
                "soul": 1,
                "still": 1,
                "stole": 1,
                "sub": 1,
                "subs": 1,
                "sweat": 1,
                "tha": 1,
                "thanks": 1,
                "time": 1,
                "toooo": 1,
                "touches": 1,
                "upload": 1,
                "vedio": 1,
                "version": 3,
                "vibes": 1,
                "video": 14,
                "wala": 2,
                "wonderful": 1,
                "world": 1,
                "ye": 1,
                "yhi": 1,
                "Но": 1,
                "Представляете": 1,
                "блогеров": 1,
                "должен": 1,
                "здесь": 1,
                "и": 1,
                "лидер": 1,
                "не": 1,
                "подписаться": 1,
                "понял": 1,
                "почему": 1,
                "самый": 1,
                "сегодня": 1,
                "среди": 1,
                "так": 1,
                "только": 1,
                "узнал": 1,
                "хорошего": 1,
                "что": 1,
                "это": 1,
                "ютуба": 1,
                "я": 1,
                "أحد": 1,
                "أصدقائي": 1,
                "أغنية": 1,
                "أن": 1,
                "الأغنية": 1,
                "الأيام": 1,
                "الإسم": 1,
                "الصحيح": 1,
                "الهنود": 1,
                "تقول": 1,
                "تكتبوا": 1,
                "سمعت": 1,
                "في": 1,
                "كلماتها": 1,
                "لتلك": 1,
                "لقد": 1,
                "لي": 1,
                "هل": 1,
                "هندية": 1,
                "يا": 1,
                "يمكنكم": 1,
                "एक": 1,
                "क": 1,
                "ग": 1,
                "त": 1,
                "न": 1,
                "प": 1,
                "भ": 1,
                "म": 1,
                "य": 1,
                "रस": 1,
                "ह": 1,
                "অন": 1,
                "অনন": 1,
                "আছ": 1,
                "আপন": 1,
                "আব": 1,
                "আম": 1,
                "ঈশ": 1,
                "এখন": 1,
                "এব": 1,
                "এস": 1,
                "ক": 1,
                "কর": 1,
                "করছ": 1,
                "খ": 1,
                "ছ": 1,
                "জ": 1,
                "জন": 1,
                "ঠ": 1,
                "ড": 1,
                "ত": 1,
                "থ": 1,
                "দ": 1,
                "ন": 1,
                "নদ": 1,
                "নর": 1,
                "প": 1,
                "পথ": 1,
                "ব": 1,
                "বন": 1,
                "বর": 1,
                "বস": 1,
                "ম": 1,
                "মন": 1,
                "য": 1,
                "র": 1,
                "শ": 1,
                "স": 1,
                "সরণ": 1,
                "হয": 1,
                "내": 1,
                "배우이자": 1,
                "여배우": 1,
                "최고의": 1
            },
            "Comments Count": "96",
            "Title": "Raat Baaki (Lyrical)SatyaPrem Ki Katha |Kartik,Kiara|Meet Bros, Monali,Piyush|Kumaar|Sajid N,Sameer",
            "sentiment_score": 0.2671558441558443
        },
        {
            "Comment_word_cloud": {
                "3rd": 1,
                "3য": 1,
                "Aaryan": 1,
                "Advani": 1,
                "Always": 1,
                "Arijit": 29,
                "Arjit": 3,
                "Awesome": 1,
                "Bagchi": 1,
                "Beautiful": 1,
                "Better": 1,
                "Beutiful": 1,
                "Biggest": 1,
                "Bollywood": 2,
                "Boss": 1,
                "C00l": 1,
                "Currently": 1,
                "Dear": 1,
                "Deserve": 1,
                "Ek": 1,
                "Era": 1,
                "Favourite": 1,
                "Fill": 1,
                "G": 1,
                "Goosebump": 1,
                "Hayeeee": 1,
                "Karthik": 1,
                "Kartik": 2,
                "Kiara": 1,
                "King": 2,
                "Kis": 2,
                "Kishore": 1,
                "Kumar": 1,
                "Lagend": 1,
                "Le": 1,
                "Lots": 1,
                "Love": 2,
                "Magical": 1,
                "Masterpiece": 1,
                "Mujhe": 1,
                "Nepal": 1,
                "Nice": 5,
                "Nu": 1,
                "One": 1,
                "Oxygen": 1,
                "Pasoori": 1,
                "Perfect": 1,
                "Shing": 1,
                "Singh": 22,
                "Sir": 1,
                "SoNg": 1,
                "Song": 1,
                "Sostar": 1,
                "Spotify": 1,
                "Super": 2,
                "Superb": 1,
                "Thank": 1,
                "Tum": 1,
                "U": 1,
                "Unbelievable": 1,
                "Unstopable": 1,
                "Views": 1,
                "Waiting": 1,
                "Whoever": 1,
                "Wonderful": 1,
                "Wow": 3,
                "Yes": 1,
                "Yrrr": 1,
                "aarhi": 1,
                "aaunga": 2,
                "accha": 2,
                "ache": 1,
                "album": 1,
                "always": 1,
                "apki": 1,
                "arijit": 4,
                "arijitiyan": 1,
                "artist": 1,
                "astitwa": 1,
                "attract": 1,
                "aunga": 1,
                "bar": 1,
                "berie": 1,
                "best": 1,
                "better": 1,
                "bole": 1,
                "bollywood": 2,
                "bolo": 1,
                "boyfriend": 1,
                "br": 5,
                "button": 1,
                "comment": 1,
                "composition": 1,
                "concert": 1,
                "couple": 1,
                "cute": 2,
                "day": 1,
                "definitely": 1,
                "different": 2,
                "duper": 1,
                "end": 1,
                "era": 1,
                "even": 1,
                "everyone": 1,
                "fan": 1,
                "fans": 1,
                "fantastic": 3,
                "favourite": 1,
                "feel": 1,
                "female": 1,
                "fine": 1,
                "first": 1,
                "future": 1,
                "gelo": 1,
                "girl": 1,
                "girlfriend": 1,
                "globally": 1,
                "god": 1,
                "great": 1,
                "guys": 1,
                "h": 1,
                "handsome": 1,
                "hi": 1,
                "ho": 1,
                "hote": 1,
                "hours": 1,
                "industry": 1,
                "jata": 1,
                "ka": 1,
                "karke": 1,
                "kgf": 2,
                "khtam": 1,
                "kii": 1,
                "ko": 3,
                "kon": 1,
                "laga": 2,
                "lagt": 1,
                "le": 1,
                "lifetime": 1,
                "lights": 1,
                "loop": 1,
                "lord": 1,
                "love": 4,
                "magic": 2,
                "mahubbat": 1,
                "man": 1,
                "mante": 1,
                "many": 2,
                "mark": 1,
                "masterpiece": 2,
                "mean": 1,
                "mein": 1,
                "mera": 1,
                "mere": 1,
                "meri": 1,
                "millions": 1,
                "mohabbat": 1,
                "monotonous": 1,
                "movie": 3,
                "much": 4,
                "mulakath": 1,
                "music": 1,
                "nahi": 1,
                "near": 1,
                "never": 2,
                "new": 1,
                "nice": 1,
                "nothing": 1,
                "notification": 1,
                "old": 1,
                "one": 2,
                "oxygen": 1,
                "parents": 1,
                "pata": 1,
                "people": 1,
                "phone": 1,
                "pray": 1,
                "pure": 1,
                "quot": 2,
                "sad": 1,
                "salaar": 2,
                "samne": 1,
                "se": 2,
                "series": 1,
                "shows": 1,
                "singer": 3,
                "singh": 5,
                "single": 1,
                "sir": 3,
                "someone": 2,
                "song": 20,
                "songs": 1,
                "soul": 1,
                "special": 1,
                "subscriber": 1,
                "syd": 1,
                "tha": 2,
                "till": 1,
                "time": 1,
                "today": 1,
                "top": 1,
                "totally": 1,
                "trending": 1,
                "unbeatable": 1,
                "unbelievable": 1,
                "varieties": 1,
                "vibe": 1,
                "views": 2,
                "voice": 6,
                "whatever": 1,
                "word": 1,
                "words": 1,
                "yaad": 1,
                "yaar": 1,
                "years": 1,
                "yerr": 1,
                "অন": 1,
                "অনন": 1,
                "আছ": 1,
                "আপন": 1,
                "আব": 1,
                "আম": 1,
                "ঈশ": 1,
                "এখন": 1,
                "এব": 1,
                "এস": 1,
                "ক": 1,
                "কর": 1,
                "করছ": 1,
                "খ": 1,
                "ছ": 1,
                "জ": 1,
                "জন": 1,
                "ঠ": 1,
                "ড": 1,
                "ত": 1,
                "থ": 1,
                "দ": 1,
                "ন": 1,
                "নদ": 1,
                "নর": 1,
                "প": 1,
                "পথ": 1,
                "ব": 1,
                "বন": 1,
                "বর": 1,
                "বস": 1,
                "ম": 1,
                "মন": 1,
                "য": 1,
                "শ": 1,
                "স": 1,
                "সরণ": 1,
                "হয": 1
            },
            "Comments Count": "196",
            "Title": "Le Aaunga (Lyrical)SatyaPrem Ki Katha |Kartik,Kiara|Tanishk Bagchi,Vayu #ArijitSingh |Sajid N,Sameer",
            "sentiment_score": 0.2206326315789474
        }
    ]
}